{
  "username": "AndrewRock_",
  "records": 1,
  "videos": [
    {
      "video": "DZ21dLP6m",
      "title": "AndrewRock__31-05-2025_11-35_7m50s",
      "file": "AndrewRock__31-05-2025_11-35_7m50s.mp4",
      "url": "https://short.icu/DZ21dLP6m",
      "poster": "https://lh3.googleusercontent.com/d/1tZsyoEcg7IhaBBQaHIrVWga1CG2n4vnZ?authuser=0",
      "urlIframe": "https://short.icu/DZ21dLP6m?thumbnail=https://lh3.googleusercontent.com/d/1tZsyoEcg7IhaBBQaHIrVWga1CG2n4vnZ?authuser=0",
      "data": "31-05-2025",
      "horario": "11-35",
      "tempo": "7m50s"
    }
  ]
}