{
  "username": "nicooo2011",
  "records": 1,
  "videos": [
    {
      "video": "cksRJrgVL",
      "title": "nicooo2011_31-05-2025_07-54_10m45s",
      "file": "nicooo2011_31-05-2025_07-54_10m45s.mp4",
      "url": "https://short.icu/cksRJrgVL",
      "poster": "https://db.xcam.gay/user/nicooo2011/cksRJrgVL.jpg",
      "urlIframe": "https://short.icu/cksRJrgVL?thumbnail=https://db.xcam.gay/user/nicooo2011/cksRJrgVL.jpg",
      "data": "31-05-2025",
      "horario": "07-54",
      "tempo": "10m45s"
    }
  ]
}