{
  "username": "Lujuria_96",
  "records": 1,
  "videos": [
    {
      "video": "4Lb3pVZZLj",
      "title": "Lujuria_96_31-05-2025_05-41_33m6s",
      "file": "Lujuria_96_31-05-2025_05-41_33m6s.mp4",
      "url": "https://short.icu/4Lb3pVZZLj",
      "poster": "https://db.xcam.gay/user/Lujuria_96/4Lb3pVZZLj.jpg",
      "urlIframe": "https://short.icu/4Lb3pVZZLj?thumbnail=https://db.xcam.gay/user/Lujuria_96/4Lb3pVZZLj.jpg",
      "data": "31-05-2025",
      "horario": "05-41",
      "tempo": "33m6s"
    }
  ]
}