{
  "username": "265hacher",
  "records": 1,
  "videos": [
    {
      "video": "NeeMle4sa",
      "title": "265hacher_31-05-2025_11-35_9m51s",
      "file": "265hacher_31-05-2025_11-35_9m51s.mp4",
      "url": "https://short.icu/NeeMle4sa",
      "poster": "https://lh3.googleusercontent.com/d/1SHTrtJOQDMOe-56YmqPYo3JtEvP7AMbr?authuser=0",
      "urlIframe": "https://short.icu/NeeMle4sa?thumbnail=https://lh3.googleusercontent.com/d/1SHTrtJOQDMOe-56YmqPYo3JtEvP7AMbr?authuser=0",
      "data": "31-05-2025",
      "horario": "11-35",
      "tempo": "9m51s"
    }
  ]
}