{
  "username": "Jangel9595",
  "records": 1,
  "videos": [
    {
      "video": "cIp5siXOf",
      "title": "Jangel9595_31-05-2025_05-41_26m54s",
      "file": "Jangel9595_31-05-2025_05-41_26m54s.mp4",
      "url": "https://short.icu/cIp5siXOf",
      "poster": "https://xcam.gay/db/user/Jangel9595/cIp5siXOf.jpg",
      "urlIframe": "https://short.icu/cIp5siXOf?thumbnail=https://xcam.gay/db/user/Jangel9595/cIp5siXOf.jpg",
      "data": "31-05-2025",
      "horario": "05-41",
      "tempo": "26m54s"
    }
  ]
}