{
  "username": "niconice87",
  "records": 1,
  "videos": [
    {
      "video": "npLXEsfBt",
      "title": "niconice87_01-06-2025_15-03_13m7s",
      "file": "niconice87_01-06-2025_15-03_13m7s.mp4",
      "url": "https://short.icu/npLXEsfBt",
      "poster": "https://db.xcam.gay/user/niconice87/npLXEsfBt.jpg",
      "urlIframe": "https://short.icu/npLXEsfBt?thumbnail=https%3A%2F%2Fdb.xcam.gay%2Fuser%2Fniconice87%2FnpLXEsfBt.jpg",
      "data": "01-06-2025",
      "horario": "15-03",
      "tempo": "13m7s"
    }
  ]
}