{
  "username": "Kebec52",
  "records": 1,
  "videos": [
    {
      "video": "xt8UoPyxy",
      "title": "Kebec52_31-05-2025_03-09_32m56s",
      "file": "Kebec52_31-05-2025_03-09_32m56s.mp4",
      "url": "https://short.icu/xt8UoPyxy",
      "poster": "https://xcam.gay/db/user/Kebec52/xt8UoPyxy.jpg",
      "urlIframe": "https://short.icu/xt8UoPyxy?thumbnail=https://xcam.gay/db/user/Kebec52/xt8UoPyxy.jpg",
      "data": "31-05-2025",
      "horario": "03-09",
      "tempo": "32m56s"
    }
  ]
}