{
  "username": "MercedesMO",
  "records": 1,
  "videos": [
    {
      "video": "dCQ_DC-4F",
      "title": "MercedesMO_01-06-2025_13-52_16m11s",
      "file": "MercedesMO_01-06-2025_13-52_16m11s.mp4",
      "url": "https://short.icu/dCQ_DC-4F",
      "poster": "https://db.xcam.gay/user/MercedesMO/dCQ_DC-4F.jpg",
      "urlIframe": "https://short.icu/dCQ_DC-4F?thumbnail=https://db.xcam.gay/user/MercedesMO/dCQ_DC-4F.jpg",
      "data": "01-06-2025",
      "horario": "13-52",
      "tempo": "16m11s"
    }
  ]
}