{
  "username": "hairysmallfat",
  "records": 1,
  "videos": [
    {
      "video": "iztpkAEAP",
      "title": "hairysmallfat_01-06-2025_13-15_33m1s",
      "file": "hairysmallfat_01-06-2025_13-15_33m1s.mp4",
      "url": "https://short.icu/iztpkAEAP",
      "poster": "https://db.xcam.gay/user/hairysmallfat/iztpkAEAP.jpg",
      "urlIframe": "https://short.icu/iztpkAEAP?thumbnail=https://db.xcam.gay/user/hairysmallfat/iztpkAEAP.jpg",
      "data": "01-06-2025",
      "horario": "13-15",
      "tempo": "33m1s"
    }
  ]
}