{
  "username": "mexica_hot",
  "records": 1,
  "videos": [
    {
      "video": "byYq5Tr6M",
      "title": "mexica_hot_31-05-2025_02-31_7m2s",
      "file": "mexica_hot_31-05-2025_02-31_7m2s.mp4",
      "url": "https://short.icu/byYq5Tr6M",
      "poster": "https://xcam.gay/db/user/mexica_hot/byYq5Tr6M.jpg",
      "urlIframe": "https://short.icu/byYq5Tr6M?thumbnail=https://xcam.gay/db/user/mexica_hot/byYq5Tr6M.jpg",
      "data": "31-05-2025",
      "horario": "02-31",
      "tempo": "7m2s"
    }
  ]
}