{
  "username": "Gatogostoso_",
  "records": 1,
  "videos": [
    {
      "video": "auz6LhOtL",
      "title": "Gatogostoso__12-06-2025_02-58_32m31s",
      "file": "Gatogostoso__12-06-2025_02-58_32m31s.mp4",
      "url": "https://short.icu/auz6LhOtL",
      "poster": "https://lh3.googleusercontent.com/d/1CJRy4D4t8qMvhxLLE1EkY3dlUGta_i0q?authuser=0",
      "urlIframe": "https://short.icu/auz6LhOtL?thumbnail=https://lh3.googleusercontent.com/d/1CJRy4D4t8qMvhxLLE1EkY3dlUGta_i0q?authuser=0",
      "data": "12-06-2025",
      "horario": "02-58",
      "tempo": "32m31s"
    }
  ]
}